OptiCon/__init__.py
OptiCon/agent.py
OptiCon/command.py
OptiCon/event.py
OptiCon/minecraft_websocket.py
OptiCon/packet.py
OptiCon/server.py
OptiCon/utils.py
OptiCon-0.0.1.dist-info/LICENSE
OptiCon-0.0.1.dist-info/METADATA
OptiCon-0.0.1.dist-info/WHEEL
OptiCon-0.0.1.dist-info/top_level.txt
OptiCon-0.0.1.dist-info/RECORD
