Metadata-Version: 2.1
Name: OptiCon
Version: 0.0.1
Summary: MinecraftWS fork that provides optimal performance and compatibility with IndigoMod.
Home-page: https://github.com/IndigoMod/OptiCon
Author: beta5051
Author-email: AcaiBerii@protonmail.com
License: MIT
Platform: UNKNOWN
Requires-Dist: websockets (>=8.1)
